ioutliers/__init__.py
ioutliers/outliers.py
ioutliers-0.1.1.dist-info/LICENSE
ioutliers-0.1.1.dist-info/METADATA
ioutliers-0.1.1.dist-info/WHEEL
ioutliers-0.1.1.dist-info/top_level.txt
ioutliers-0.1.1.dist-info/RECORD
